myguidlib/__init__.py
myguidlib/generator.py
myguidlib-0.1.dist-info/METADATA
myguidlib-0.1.dist-info/WHEEL
myguidlib-0.1.dist-info/top_level.txt
myguidlib-0.1.dist-info/RECORD
